mean_median_mode/__init__.py
mean_median_mode/data.py
mean_median_mode/meanmedianmodeclc.py
mean_median_mode-0.1.dist-info/LICENSE.txt.txt
mean_median_mode-0.1.dist-info/METADATA
mean_median_mode-0.1.dist-info/WHEEL
mean_median_mode-0.1.dist-info/top_level.txt
mean_median_mode-0.1.dist-info/RECORD
